serialmfg/__init__.py
serialmfg/api_client.py
serialmfg/config.py
serialmfg/exceptions.py
serialmfg/identifier.py
serialmfg/process.py
serialmfg/serial.py
serialmfg/serial_resources/__init__.py
serialmfg/serial_resources/component_instance.py
serialmfg/serial_resources/component_instance_link.py
serialmfg/serial_resources/dataset.py
serialmfg/serial_resources/operator.py
serialmfg/serial_resources/part_number.py
serialmfg/serial_resources/process_entry.py
serialmfg/utils/__init__.py
serialmfg/utils/time_formatting.py
tests/__init__.py
tests/constants.py
tests/unit_test.py
serialmfg-1.3.0.dist-info/LICENSE
serialmfg-1.3.0.dist-info/METADATA
serialmfg-1.3.0.dist-info/WHEEL
serialmfg-1.3.0.dist-info/top_level.txt
serialmfg-1.3.0.dist-info/RECORD
