Metadata-Version: 2.1
Name: serialmfg
Version: 1.3.0
Summary: This module provides a simple Python interface to interact with the Serial API. It allows you to easily perform common operations such as uploading process data, initializing identifiers, and checking the server connection.
Home-page: https://github.com/serialmfg/serial-py
Author: Devon Copeland
Author-email: founders@serial.io
License: MIT
Classifier: License :: OSI Approved :: MIT License
Classifier: Programming Language :: Python
Classifier: Programming Language :: Python :: 3
Classifier: Programming Language :: Python :: 3.11
License-File: LICENSE
Requires-Dist: requests
